DaguanShujuNlpTekanCongYuanliDaoShijian/README.md
DaguanShujuNlpTekanCongYuanliDaoShijian/__init__.py
DaguanShujuNlpTekanCongYuanliDaoShijian/__main__.py
DaguanShujuNlpTekanCongYuanliDaoShijian/file.pdf
DaguanShujuNlpTekanCongYuanliDaoShijian/index.html
daguan_shuju_nlp_tekan_cong_yuanli_dao_shijian-2024.3.4.0.dist-info/METADATA
daguan_shuju_nlp_tekan_cong_yuanli_dao_shijian-2024.3.4.0.dist-info/WHEEL
daguan_shuju_nlp_tekan_cong_yuanli_dao_shijian-2024.3.4.0.dist-info/entry_points.txt
daguan_shuju_nlp_tekan_cong_yuanli_dao_shijian-2024.3.4.0.dist-info/top_level.txt
daguan_shuju_nlp_tekan_cong_yuanli_dao_shijian-2024.3.4.0.dist-info/RECORD
